scrcpy/__init__.py
scrcpy/const.py
scrcpy/control.py
scrcpy/core.py
scrcpy/muti_core.py
scrcpy/scrcpy-server.jar
scrcpy_ui/__init__.py
scrcpy_ui/config_edit.ui
scrcpy_ui/main.py
scrcpy_ui/mainwindow.ui
scrcpy_ui/schemas.py
scrcpy_ui/scrcpy/__init__.py
scrcpy_ui/scrcpy/const.py
scrcpy_ui/scrcpy/control.py
scrcpy_ui/scrcpy/core.py
scrcpy_ui/scrcpy/scrcpy-server.jar
scrcpy_ui/screen.ui
scrcpy_ui/single.ui
scrcpy_ui/ui_config_edit.py
scrcpy_ui/ui_main.py
scrcpy_ui/ui_screen.py
scrcpy_ui/ui_single.py
scrcpy_ui/window_config_edit.py
scrcpy_ui/window_main.py
scrcpy_ui/window_screen.py
scrcpy_ui/window_single.py
workers/__init__.py
workers/schemas.py
workers/server.py
workers/thread_worker.py
workers/utils.py
muti_scrcpy_client-0.5.dist-info/entry_points.txt
muti_scrcpy_client-0.5.dist-info/LICENSE.txt
muti_scrcpy_client-0.5.dist-info/WHEEL
muti_scrcpy_client-0.5.dist-info/METADATA
muti_scrcpy_client-0.5.dist-info/RECORD
