Metadata-Version: 2.1
Name: muti-scrcpy-client
Version: 0.5
Summary: A muticlient of scrcpy
Home-page: https://github.com/IanVzs/py-muti-scrcpy
License: MIT
Author: ianvzs
Author-email: ianvzs@outlook.com
Requires-Python: >=3.7,<=3.10.4
Classifier: License :: OSI Approved :: MIT License
Classifier: Programming Language :: Python :: 3
Classifier: Programming Language :: Python :: 3.10
Classifier: Programming Language :: Python :: 3.7
Classifier: Programming Language :: Python :: 3.8
Classifier: Programming Language :: Python :: 3.9
Provides-Extra: ui
Requires-Dist: PySide6 (>=6.0.0,<7.0.0); extra == "ui"
Requires-Dist: adbutils (>=0.11.0,<0.12.0)
Requires-Dist: av (>=8.0.3,<9.0.0)
Requires-Dist: click (>=7.0.0,<8.0.0); extra == "ui"
Requires-Dist: loguru (>=0.6.0,<0.7.0)
Requires-Dist: opencv-python (>=4.5.3,<5.0.0)
Requires-Dist: pydantic (>=1.9.0,<2.0.0)
Project-URL: Repository, https://github.com/IanVzs/py-muti-scrcpy
